sel_pom/__init__.py
sel_pom/__main__.py
sel_pom/template/main.py
sel_pom/template/config/config.py
sel_pom/template/pages/__init__.py
sel_pom/template/pages/base_page.py
sel_pom/template/utils/__init__.py
sel_pom/template/utils/driver_factory.py
sel_pom-0.0.1.dist-info/METADATA
sel_pom-0.0.1.dist-info/WHEEL
sel_pom-0.0.1.dist-info/entry_points.txt
sel_pom-0.0.1.dist-info/top_level.txt
sel_pom-0.0.1.dist-info/RECORD
