Metadata-Version: 2.4
Name: sel-pom
Version: 0.0.1
Summary: A simple CLI to create a Selenium POM project structure.
Author-email: Your Name <you@example.com>
Project-URL: Homepage, https://github.com/pypa/sampleproject
Project-URL: Bug Tracker, https://github.com/pypa/sampleproject/issues
Classifier: Programming Language :: Python :: 3
Classifier: License :: OSI Approved :: MIT License
Classifier: Operating System :: OS Independent
Requires-Python: >=3.7
Requires-Dist: click
